<?xml version="1.0" encoding="utf-8" ?>
<dwsync>
<file name="kendo.black.min.css.map" server="20.246.185.28" local="132516203732994777" remote="133373427000000000" Dst="2" />
<file name="kendo.black.min.css" server="20.246.185.28" local="132516203699636803" remote="133373427000000000" Dst="2" />
<file name="kendo.black.mobile.min.css" server="20.246.185.28" local="132516203735915423" remote="133373427000000000" Dst="2" />
<file name="kendo.black.mobile.min.css.map" server="20.246.185.28" local="132516203734125024" remote="133373427000000000" Dst="2" />
<file name="kendo.blueopal.min.css" server="20.246.185.28" local="132516203720721424" remote="133373427000000000" Dst="2" />
<file name="kendo.blueopal.min.css.map" server="20.246.185.28" local="132516203735065227" remote="133373427000000000" Dst="2" />
<file name="kendo.blueopal.mobile.min.css" server="20.246.185.28" local="132516203719331112" remote="133373427000000000" Dst="2" />
<file name="kendo.blueopal.mobile.min.css.map" server="20.246.185.28" local="132516203703667614" remote="133373427000000000" Dst="2" />
<file name="kendo.bootstrap-v4.css" server="20.246.185.28" local="132516203704527801" remote="133373427000000000" Dst="2" />
<file name="kendo.bootstrap-v4.min.css" server="20.246.185.28" local="132516203745191871" remote="133373427000000000" Dst="2" />
<file name="kendo.bootstrap-v4.min.css.map" server="20.246.185.28" local="132516203733344858" remote="133373427000000000" Dst="2" />
<file name="kendo.bootstrap.min.css" server="20.246.185.28" local="132516203725012475" remote="133373427000000000" Dst="2" />
<file name="kendo.bootstrap.min.css.map" server="20.246.185.28" local="132516203704147811" remote="133373427000000000" Dst="2" />
<file name="kendo.bootstrap.mobile.min.css" server="20.246.185.28" local="132516203703347538" remote="133373427000000000" Dst="2" />
<file name="kendo.bootstrap.mobile.min.css.map" server="20.246.185.28" local="132516203699906781" remote="133373427000000000" Dst="2" />
<file name="kendo.common-bootstrap.min.css.map" server="20.246.185.28" local="132516203699816751" remote="133373427000000000" Dst="2" />
<file name="kendo.common-bootstrap.min.css" server="20.246.185.28" local="132516203706598373" remote="133373427000000000" Dst="2" />
<file name="kendo.common-fiori.min.css" server="20.246.185.28" local="132516203736930042" remote="133373427000000000" Dst="2" />
<file name="kendo.common-fiori.min.css.map" server="20.246.185.28" local="132516203703757724" remote="133373427000000000" Dst="2" />
<file name="kendo.common-material.min.css" server="20.246.185.28" local="132516203737560177" remote="133373427000000000" Dst="2" />
<file name="kendo.common-material.min.css.map" server="20.246.185.28" local="132516203726712766" remote="133373427000000000" Dst="2" />
<file name="kendo.common-nova.min.css" server="20.246.185.28" local="132516203721061499" remote="133373427000000000" Dst="2" />
<file name="kendo.common-nova.min.css.map" server="20.246.185.28" local="132516203737430128" remote="133373427000000000" Dst="2" />
<file name="kendo.common-office365.min.css" server="20.246.185.28" local="132516203737140167" remote="133373427000000000" Dst="2" />
<file name="kendo.common-office365.min.css.map" server="20.246.185.28" local="132516203739270551" remote="133373427000000000" Dst="2" />
<file name="kendo.common.min.css" server="20.246.185.28" local="132516203698666584" remote="133373427000000000" Dst="2" />
<file name="kendo.common.min.css.map" server="20.246.185.28" local="132516203724252220" remote="133373427000000000" Dst="2" />
<file name="kendo.dataviz.black.min.css" server="20.246.185.28" local="132516203723802115" remote="133373427000000000" Dst="2" />
<file name="kendo.dataviz.black.min.css.map" server="20.246.185.28" local="132516203740270777" remote="133373427000000000" Dst="2" />
<file name="kendo.dataviz.blueopal.min.css" server="20.246.185.28" local="132516203698966657" remote="133373427000000000" Dst="2" />
<file name="kendo.dataviz.blueopal.min.css.map" server="20.246.185.28" local="132516203725962589" remote="133373427000000000" Dst="2" />
<file name="kendo.dataviz.bootstrap.min.css" server="20.246.185.28" local="132516203700476995" remote="133373427000000000" Dst="2" />
<file name="kendo.dataviz.bootstrap.min.css.map" server="20.246.185.28" local="132516203735455325" remote="133373427000000000" Dst="2" />
<file name="kendo.dataviz.default.min.css" server="20.246.185.28" local="132516203736619963" remote="133373427000000000" Dst="2" />
<file name="kendo.dataviz.fiori.min.css" server="20.246.185.28" local="132516203739380575" remote="133373427000000000" Dst="2" />
<file name="kendo.dataviz.default.min.css.map" server="20.246.185.28" local="132516203737320102" remote="133373427000000000" Dst="2" />
<file name="kendo.dataviz.fiori.min.css.map" server="20.246.185.28" local="132516203703127492" remote="133373427000000000" Dst="2" />
<file name="kendo.dataviz.flat.min.css.map" server="20.246.185.28" local="132516203726182646" remote="133373427000000000" Dst="2" />
<file name="kendo.dataviz.flat.min.css" server="20.246.185.28" local="132516203719101057" remote="133373427000000000" Dst="2" />
<file name="kendo.dataviz.highcontrast.min.css" server="20.246.185.28" local="132516203724702405" remote="133373427000000000" Dst="2" />
<file name="kendo.dataviz.material.min.css" server="20.246.185.28" local="132516203725192422" remote="133373427000000000" Dst="2" />
<file name="kendo.dataviz.highcontrast.min.css.map" server="20.246.185.28" local="132516203739890678" remote="133373427000000000" Dst="2" />
<file name="kendo.dataviz.material.min.css.map" server="20.246.185.28" local="132516203733804962" remote="133373427000000000" Dst="2" />
<file name="kendo.dataviz.materialblack.min.css.map" server="20.246.185.28" local="132516203737760207" remote="133373427000000000" Dst="2" />
<file name="kendo.dataviz.materialblack.min.css" server="20.246.185.28" local="132516203703037473" remote="133373427000000000" Dst="2" />
<file name="kendo.dataviz.metro.min.css" server="20.246.185.28" local="132516203726402697" remote="133373427000000000" Dst="2" />
<file name="kendo.dataviz.metroblack.min.css" server="20.246.185.28" local="132516203698436435" remote="133373427000000000" Dst="2" />
<file name="kendo.dataviz.metro.min.css.map" server="20.246.185.28" local="132516203737220184" remote="133373427000000000" Dst="2" />
<file name="kendo.dataviz.metroblack.min.css.map" server="20.246.185.28" local="132516203703967682" remote="133373427000000000" Dst="2" />
<file name="kendo.dataviz.min.css" server="20.246.185.28" local="132516203733474890" remote="133373427000000000" Dst="2" />
<file name="kendo.dataviz.min.css.map" server="20.246.185.28" local="132516203735715484" remote="133373427000000000" Dst="2" />
<file name="kendo.dataviz.mobile.min.css.map" server="20.246.185.28" local="132516203719201074" remote="133373427000000000" Dst="2" />
<file name="kendo.dataviz.moonlight.min.css" server="20.246.185.28" local="132516203726292668" remote="133373427000000000" Dst="2" />
<file name="kendo.dataviz.mobile.min.css" server="20.246.185.28" local="132516203700616921" remote="133373427000000000" Dst="2" />
<file name="kendo.dataviz.moonlight.min.css.map" server="20.246.185.28" local="132516203720601398" remote="133373427000000000" Dst="2" />
<file name="kendo.dataviz.nova.min.css" server="20.246.185.28" local="132516203737680191" remote="133373427000000000" Dst="2" />
<file name="kendo.dataviz.nova.min.css.map" server="20.246.185.28" local="132516203725092495" remote="133373427000000000" Dst="2" />
<file name="kendo.dataviz.office365.min.css" server="20.246.185.28" local="132516203733704932" remote="133373427000000000" Dst="2" />
<file name="kendo.dataviz.office365.min.css.map" server="20.246.185.28" local="132516203698856537" remote="133373427000000000" Dst="2" />
<file name="kendo.dataviz.silver.min.css" server="20.246.185.28" local="132516203732884744" remote="133373427000000000" Dst="2" />
<file name="kendo.dataviz.silver.min.css.map" server="20.246.185.28" local="132516203699056580" remote="133373427000000000" Dst="2" />
<file name="kendo.dataviz.uniform.min.css.map" server="20.246.185.28" local="132516203732764729" remote="133373427000000000" Dst="2" />
<file name="kendo.dataviz.uniform.min.css" server="20.246.185.28" local="132516203724602292" remote="133373427000000000" Dst="2" />
<file name="kendo.default-v2.css" server="20.246.185.28" local="132516203736789998" remote="133373427000000000" Dst="2" />
<file name="kendo.default-v2.min.css.map" server="20.246.185.28" local="132516203725592515" remote="133373427000000000" Dst="2" />
<file name="kendo.default-v2.min.css" server="20.246.185.28" local="132516203723972245" remote="133373427000000000" Dst="2" />
<file name="kendo.default.min.css" server="20.246.185.28" local="132516203700736958" remote="133373427000000000" Dst="2" />
<file name="kendo.default.mobile.min.css" server="20.246.185.28" local="132516203699516680" remote="133373427000000000" Dst="2" />
<file name="kendo.default.min.css.map" server="20.246.185.28" local="132516203735805405" remote="133373427000000000" Dst="2" />
<file name="kendo.default.mobile.min.css.map" server="20.246.185.28" local="132516203736115471" remote="133373427000000000" Dst="2" />
<file name="kendo.fiori.min.css" server="20.246.185.28" local="132516203734985315" remote="133373427000000000" Dst="2" />
<file name="kendo.fiori.min.css.map" server="20.246.185.28" local="132516203723342101" remote="133373427000000000" Dst="2" />
<file name="kendo.fiori.mobile.min.css.map" server="20.246.185.28" local="132516203719431134" remote="133373427000000000" Dst="2" />
<file name="kendo.fiori.mobile.min.css" server="20.246.185.28" local="132516203721171617" remote="133373427000000000" Dst="2" />
<file name="kendo.flat.min.css" server="20.246.185.28" local="132516203703457567" remote="133373427000000000" Dst="2" />
<file name="kendo.flat.min.css.map" server="20.246.185.28" local="132516203737010139" remote="133373427000000000" Dst="2" />
<file name="kendo.flat.mobile.min.css" server="20.246.185.28" local="132516203736319882" remote="133373427000000000" Dst="2" />
<file name="kendo.flat.mobile.min.css.map" server="20.246.185.28" local="132516203725292439" remote="133373427000000000" Dst="2" />
<file name="kendo.highcontrast.min.css" server="20.246.185.28" local="132516203703877658" remote="133373427000000000" Dst="2" />
<file name="kendo.highcontrast.min.css.map" server="20.246.185.28" local="132516203735545443" remote="133373427000000000" Dst="2" />
<file name="kendo.highcontrast.mobile.min.css" server="20.246.185.28" local="132516203703577603" remote="133373427000000000" Dst="2" />
<file name="kendo.highcontrast.mobile.min.css.map" server="20.246.185.28" local="132516203698526463" remote="133373427000000000" Dst="2" />
<file name="kendo.material-v2.css" server="20.246.185.28" local="132516203702917474" remote="133373427000000000" Dst="2" />
<file name="kendo.material-v2.min.css" server="20.246.185.28" local="132516203704347753" remote="133373427000000000" Dst="2" />
<file name="kendo.material-v2.min.css.map" server="20.246.185.28" local="132516203739800666" remote="133373427000000000" Dst="2" />
<file name="kendo.material.min.css" server="20.246.185.28" local="132516203700366964" remote="133373427600000000" Dst="2" />
<file name="kendo.material.min.css.map" server="20.246.185.28" local="132516203726492707" remote="133373427600000000" Dst="2" />
<file name="kendo.material.mobile.min.css" server="20.246.185.28" local="132516203723462035" remote="133373427600000000" Dst="2" />
<file name="kendo.material.mobile.min.css.map" server="20.246.185.28" local="132516203734215129" remote="133373427600000000" Dst="2" />
<file name="kendo.materialblack.min.css" server="20.246.185.28" local="132516203733935000" remote="133373427600000000" Dst="2" />
<file name="kendo.materialblack.min.css.map" server="20.246.185.28" local="132516203727262891" remote="133373427600000000" Dst="2" />
<file name="kendo.materialblack.mobile.min.css" server="20.246.185.28" local="132516203735245272" remote="133373427600000000" Dst="2" />
<file name="kendo.metro.min.css" server="20.246.185.28" local="132516203735365396" remote="133373427600000000" Dst="2" />
<file name="kendo.materialblack.mobile.min.css.map" server="20.246.185.28" local="132516203699266618" remote="133373427600000000" Dst="2" />
<file name="kendo.metro.min.css.map" server="20.246.185.28" local="132516203725872575" remote="133373427600000000" Dst="2" />
<file name="kendo.metro.mobile.min.css.map" server="20.246.185.28" local="132516203733584911" remote="133373427600000000" Dst="2" />
<file name="kendo.metro.mobile.min.css" server="20.246.185.28" local="132516203725412569" remote="133373427600000000" Dst="2" />
<file name="kendo.metroblack.min.css" server="20.246.185.28" local="132516203726612743" remote="133373427600000000" Dst="2" />
<file name="kendo.metroblack.min.css.map" server="20.246.185.28" local="132516203723252087" remote="133373427600000000" Dst="2" />
<file name="kendo.metroblack.mobile.min.css" server="20.246.185.28" local="132516203702747410" remote="133373427600000000" Dst="2" />
<file name="kendo.metroblack.mobile.min.css.map" server="20.246.185.28" local="132516203704717835" remote="133373427600000000" Dst="2" />
<file name="kendo.mobile.all.min.css.map" server="20.246.185.28" local="132516203734665243" remote="133373427600000000" Dst="2" />
<file name="kendo.mobile.all.min.css" server="20.246.185.28" local="132516203724392248" remote="133373427600000000" Dst="2" />
<file name="kendo.mobile.android.dark.min.css" server="20.246.185.28" local="132516203699386651" remote="133373427600000000" Dst="2" />
<file name="kendo.mobile.android.dark.min.css.map" server="20.246.185.28" local="132516203702627370" remote="133373427600000000" Dst="2" />
<file name="kendo.mobile.android.light.min.css.map" server="20.246.185.28" local="132516203703217507" remote="133373427600000000" Dst="2" />
<file name="kendo.mobile.android.light.min.css" server="20.246.185.28" local="132516203726092621" remote="133373427600000000" Dst="2" />
<file name="kendo.mobile.blackberry.min.css" server="20.246.185.28" local="132516203732684699" remote="133373427600000000" Dst="2" />
<file name="kendo.mobile.blackberry.min.css.map" server="20.246.185.28" local="132516203704057702" remote="133373427600000000" Dst="2" />
<file name="kendo.mobile.common.min.css" server="20.246.185.28" local="132516203700026890" remote="133373427600000000" Dst="2" />
<file name="kendo.mobile.common.min.css.map" server="20.246.185.28" local="132516203723682085" remote="133373427600000000" Dst="2" />
<file name="kendo.mobile.fiori.min.css.map" server="20.246.185.28" local="132516203739980802" remote="133373427600000000" Dst="2" />
<file name="kendo.mobile.fiori.min.css" server="20.246.185.28" local="132516203726832791" remote="133373427600000000" Dst="2" />
<file name="kendo.mobile.flat.min.css" server="20.246.185.28" local="132516203733144807" remote="133373427600000000" Dst="2" />
<file name="kendo.mobile.ios.min.css.map" server="20.246.185.28" local="132516203700126820" remote="133373427600000000" Dst="2" />
<file name="kendo.mobile.flat.min.css.map" server="20.246.185.28" local="132516203727052839" remote="133373427600000000" Dst="2" />
<file name="kendo.mobile.ios.min.css" server="20.246.185.28" local="132516203724812430" remote="133373427600000000" Dst="2" />
<file name="kendo.mobile.material.min.css.map" server="20.246.185.28" local="132516203724492263" remote="133373427600000000" Dst="2" />
<file name="kendo.mobile.material.min.css" server="20.246.185.28" local="132516203720831440" remote="133373427600000000" Dst="2" />
<file name="kendo.mobile.meego.min.css.map" server="20.246.185.28" local="132516203734755172" remote="133373427600000000" Dst="2" />
<file name="kendo.mobile.meego.min.css" server="20.246.185.28" local="132516203734865196" remote="133373427600000000" Dst="2" />
<file name="kendo.mobile.nova.min.css.map" server="20.246.185.28" local="132516203720921469" remote="133373427600000000" Dst="2" />
<file name="kendo.mobile.nova.min.css" server="20.246.185.28" local="132516203699166697" remote="133373427600000000" Dst="2" />
<file name="kendo.mobile.office365.min.css.map" server="20.246.185.28" local="132516203735635368" remote="133373427600000000" Dst="2" />
<file name="kendo.mobile.office365.min.css" server="20.246.185.28" local="132516203723582075" remote="133373427600000000" Dst="2" />
<file name="kendo.mobile.wp8.min.css" server="20.246.185.28" local="132516203719571168" remote="133373427600000000" Dst="2" />
<file name="kendo.mobile.wp8.min.css.map" server="20.246.185.28" local="132516203736205493" remote="133373427600000000" Dst="2" />
<file name="kendo.moonlight.min.css" server="20.246.185.28" local="132516203736509933" remote="133373427600000000" Dst="2" />
<file name="kendo.moonlight.min.css.map" server="20.246.185.28" local="132516203736409913" remote="133373427600000000" Dst="2" />
<file name="kendo.moonlight.mobile.min.css.map" server="20.246.185.28" local="132516203740180855" remote="133373427600000000" Dst="2" />
<file name="kendo.moonlight.mobile.min.css" server="20.246.185.28" local="132516203736025454" remote="133373427600000000" Dst="2" />
<file name="kendo.nova.min.css" server="20.246.185.28" local="132516203739500694" remote="133373427600000000" Dst="2" />
<file name="kendo.nova.min.css.map" server="20.246.185.28" local="132516203700236847" remote="133373427600000000" Dst="2" />
<file name="kendo.nova.mobile.min.css" server="20.246.185.28" local="132516203740090728" remote="133373427600000000" Dst="2" />
<file name="kendo.nova.mobile.min.css.map" server="20.246.185.28" local="132516203699716731" remote="133373427600000000" Dst="2" />
<file name="kendo.office365.min.css" server="20.246.185.28" local="132516203739610728" remote="133373427600000000" Dst="2" />
<file name="kendo.office365.mobile.min.css" server="20.246.185.28" local="132516203726952811" remote="133373427600000000" Dst="2" />
<file name="kendo.office365.min.css.map" server="20.246.185.28" local="132516203725782559" remote="133373427600000000" Dst="2" />
<file name="kendo.office365.mobile.min.css.map" server="20.246.185.28" local="132516203724902359" remote="133373427600000000" Dst="2" />
<file name="kendo.rtl.min.css.map" server="20.246.185.28" local="132516203721261552" remote="133373427600000000" Dst="2" />
<file name="kendo.rtl.min.css" server="20.246.185.28" local="132516203718971029" remote="133373427600000000" Dst="2" />
<file name="kendo.silver.min.css" server="20.246.185.28" local="132516203698776529" remote="133373427600000000" Dst="2" />
<file name="kendo.silver.min.css.map" server="20.246.185.28" local="132516203732334719" remote="133373427600000000" Dst="2" />
<file name="kendo.silver.mobile.min.css" server="20.246.185.28" local="132516203732454648" remote="133373427600000000" Dst="2" />
<file name="kendo.silver.mobile.min.css.map" server="20.246.185.28" local="132516203704627819" remote="133373427600000000" Dst="2" />
<file name="kendo.uniform.min.css" server="20.246.185.28" local="132516203727172969" remote="133373427600000000" Dst="2" />
<file name="kendo.uniform.mobile.min.css" server="20.246.185.28" local="132516203723172068" remote="133373427600000000" Dst="2" />
<file name="kendo.uniform.min.css.map" server="20.246.185.28" local="132516203734035088" remote="133373427600000000" Dst="2" />
<file name="kendo.uniform.mobile.min.css.map" server="20.246.185.28" local="132516203725692532" remote="133373427600000000" Dst="2" />
</dwsync>